evdevremapkeys/__init__.py
evdevremapkeys/evdevremapkeys.py
evdevremapkeys-1.0.2.dist-info/METADATA
evdevremapkeys-1.0.2.dist-info/WHEEL
evdevremapkeys-1.0.2.dist-info/entry_points.txt
evdevremapkeys-1.0.2.dist-info/licenses/LICENSE
evdevremapkeys-1.0.2.dist-info/RECORD
