Metadata-Version: 2.4
Name: evdevremapkeys
Version: 1.0.2
Summary: A daemon to remap key events on linux input devices
Project-URL: Homepage, https://github.com/philipl/evdevremapkeys
Author-email: Philip Langdale <philipl@overt.org>
License-Expression: MIT
License-File: LICENSE
Keywords: evdev,uinput
Requires-Python: >=3.9
Requires-Dist: evdev>=1.3.0
Requires-Dist: pyudev>=0.22.0
Requires-Dist: pyxdg>=0.26
Requires-Dist: pyyaml>=5.3
